aithermal/__init__.py
aithermal/frame_runner.py
aithermal/runner.py
aithermal/utils.py
aithermal-0.2.13.dist-info/WHEEL
aithermal-0.2.13.dist-info/METADATA
aithermal-0.2.13.dist-info/RECORD
