Metadata-Version: 2.1
Name: aithermal
Version: 0.2.13
Summary: 
Author: mjaquier
Author-email: mjaquier@me.com
Requires-Python: >=3.7,<4.0
Classifier: Programming Language :: Python :: 3
Classifier: Programming Language :: Python :: 3.7
Classifier: Programming Language :: Python :: 3.8
Requires-Dist: PyYAML (>=5.3.1,<6.0.0)
Requires-Dist: aihelper (>=0.1.9,<0.2.0)
Requires-Dist: oyaml (>=0.9,<0.10)
Requires-Dist: pandas (>=1.0.3,<2.0.0)
Requires-Dist: scipy (>=1.4.1,<2.0.0)
Requires-Dist: simplelogging (>=0.10.0,<0.11.0)
Requires-Dist: xlsxwriter (>=1.2.8,<2.0.0)
